README.rst
setup.cfg
setup.py
aboutname/__init__.py
aboutname/meaning.py
aboutname.egg-info/PKG-INFO
aboutname.egg-info/SOURCES.txt
aboutname.egg-info/dependency_links.txt
aboutname.egg-info/top_level.txt