Metadata-Version: 1.0
Name: aboutname
Version: 0.1
Summary: know your name meaning
Home-page: https://github.com/umeshdhakar/name-meaning
Author: Umesh
Author-email: kumar886umesh@gmail.com
License: UNKNOWN
Keywords: name,meaning
Platform: UNKNOWN
